.gitignore
.pylintrc
.readthedocs.yml
.travis.yml
CODE_OF_CONDUCT.md
LICENSE
README.rst
i2c_button.py
requirements.txt
setup.py
.github/workflows/build.yml
.github/workflows/release.yml
circuitpython_i2c_button.egg-info/PKG-INFO
circuitpython_i2c_button.egg-info/SOURCES.txt
circuitpython_i2c_button.egg-info/dependency_links.txt
circuitpython_i2c_button.egg-info/requires.txt
circuitpython_i2c_button.egg-info/top_level.txt
docs/api.rst
docs/conf.py
docs/examples.rst
docs/index.rst
docs/_static/favicon.ico
examples/i2c_button_2_buttons.py
examples/i2c_button_change_address.py
examples/i2c_button_polling.py
examples/i2c_button_simpletest.py
lib/i2c_button.mpy