Metadata-Version: 2.1
Name: circuitpython-i2c-button
Version: 2.2.1
Summary: CircuitPython I2C Button à la Sparkfun Qwiic Button/Switch/Arcade
Home-page: https://github.com/gmparis/CircuitPython_I2C_Button
Author: Gregory M Paris
Author-email: gregory@paris.name
License: MIT
Keywords: adafruit circuitpython micropython sparkfun i2c_button
Platform: UNKNOWN
Classifier: Development Status :: 3 - Alpha
Classifier: Intended Audience :: Developers
Classifier: Topic :: Software Development :: Libraries
Classifier: Topic :: System :: Hardware
Classifier: License :: OSI Approved :: MIT License
Classifier: Programming Language :: Python :: 3
Classifier: Programming Language :: Python :: 3.4
Classifier: Programming Language :: Python :: 3.5
